openpeople/__init__.py
openpeople/curated.py
openpeople/io.py
openpeople/types.py
openpeople/validate.py
openpeople/data/curated/P001/metadata.json
openpeople/data/curated/P001/assets/amateur_posture.jpg
openpeople/data/curated/P001/assets/amateur_selfie.jpg
openpeople/data/curated/P001/assets/character_sheet.jpg
openpeople/data/curated/P001/assets/emotions_sheet.jpg
openpeople/data/curated/P001/assets/studio_portrait.jpg
openpeople/data/curated/P001/assets/studio_posture.jpg
openpeople/data/curated/P002/metadata.json
openpeople/data/curated/P002/assets/amateur_posture.jpg
openpeople/data/curated/P002/assets/amateur_selfie.jpg
openpeople/data/curated/P002/assets/character_sheet.jpg
openpeople/data/curated/P002/assets/emotions_sheet.jpg
openpeople/data/curated/P002/assets/studio_portrait.jpg
openpeople/data/curated/P002/assets/studio_posture.jpg
openpeople/data/curated/P003/metadata.json
openpeople/data/curated/P003/assets/amateur_posture.jpg
openpeople/data/curated/P003/assets/amateur_selfie.jpg
openpeople/data/curated/P003/assets/character_sheet.jpg
openpeople/data/curated/P003/assets/emotions_sheet.jpg
openpeople/data/curated/P003/assets/studio_portrait.jpg
openpeople/data/curated/P003/assets/studio_posture.jpg
openpeople/data/curated/P004/metadata.json
openpeople/data/curated/P004/assets/amateur_posture.jpg
openpeople/data/curated/P004/assets/amateur_selfie.jpg
openpeople/data/curated/P004/assets/character_sheet.jpg
openpeople/data/curated/P004/assets/emotions_sheet.jpg
openpeople/data/curated/P004/assets/studio_portrait.jpg
openpeople/data/curated/P004/assets/studio_posture.jpg
openpeople/data/curated/P005/metadata.json
openpeople/data/curated/P005/assets/amateur_posture.jpg
openpeople/data/curated/P005/assets/amateur_selfie.jpg
openpeople/data/curated/P005/assets/character_sheet.jpg
openpeople/data/curated/P005/assets/emotions_sheet.jpg
openpeople/data/curated/P005/assets/studio_portrait.jpg
openpeople/data/curated/P005/assets/studio_posture.jpg
openpeople-0.1.2.dist-info/METADATA
openpeople-0.1.2.dist-info/WHEEL
openpeople-0.1.2.dist-info/licenses/LICENSE
openpeople-0.1.2.dist-info/RECORD
