Metadata-Version: 2.4
Name: openpeople
Version: 0.1.2
Summary: Dataset of synthetic people for testing generative image/video pipelines at scale
Project-URL: Homepage, https://github.com/Prompt-Haus/OpenPeople
Project-URL: Repository, https://github.com/Prompt-Haus/OpenPeople
Project-URL: Issues, https://github.com/Prompt-Haus/OpenPeople/issues
Author: Prompt Haus
License-Expression: MIT
License-File: LICENSE
Keywords: dataset,generative,image-generation,people,synthetic,testing,video-generation
Classifier: Development Status :: 3 - Alpha
Classifier: Intended Audience :: Developers
Classifier: License :: OSI Approved :: MIT License
Classifier: Programming Language :: Python :: 3
Classifier: Programming Language :: Python :: 3.9
Classifier: Programming Language :: Python :: 3.10
Classifier: Programming Language :: Python :: 3.11
Classifier: Programming Language :: Python :: 3.12
Classifier: Topic :: Scientific/Engineering :: Artificial Intelligence
Requires-Python: >=3.9
Requires-Dist: pydantic>=2.0
Provides-Extra: dev
Requires-Dist: pytest-cov>=4.0; extra == 'dev'
Requires-Dist: pytest>=7.0; extra == 'dev'
Provides-Extra: images
Requires-Dist: pillow>=9.0; extra == 'images'
